<?xml version="1.0" encoding="UTF-8" standalone="yes"?>

<item>
<title>Sport Live</title>
<thumbnail></thumbnail>
<fanart></fanart>
<link>http://ignoreme</link>
<externallink>https://raw.githubusercontent.com/Rhdelo/repositorioRHDELO/master/plugin.video.rhdeloiptv/menuEstadio.xml</externallink>
</item>


<item>
<title>Sport 2</title>
<thumbnail>https://i.imgur.com/Hzw9zzY.png</thumbnail>
<fanart>https://i.imgur.com/77ZkVf1.jpg</fanart>
<link>http://ignoreme</link>
<externallink>https://raw.githubusercontent.com/Rhdelo/repositorioRHDELO/master/plugin.video.rhdeloiptv/fspor.xml</externallink>
</item>

