<?xml version="1.0" encoding="UTF-8" standalone="yes"?>

<item>
<title>TV PREMIUM</title>
<thumbnail></thumbnail>
<fanart></fanart>
<link>http://ignoreme</link>
<externallink>https://raw.githubusercontent.com/Rhdelo/repositorioRHDELO/master/plugin.video.rhdeloiptv/tiviespa.xml</externallink>
</item>

<item>
<title>Cine Premium</title>
<thumbnail>https://i.imgur.com/6pD38mm.png</thumbnail>
<fanart>https://i.imgur.com/J62chtc.png</fanart>
<link>http://ignoreme</link>
<externallink>https://raw.githubusercontent.com/Rhdelo/repositorioRHDELO/master/plugin.video.rhdeloiptv/carteleraPremium.xml</externallink>
</item>

<item>
<title>Videoclub Premium</title>
<thumbnail>https://i.imgur.com/KiRFAKP.png</thumbnail>
<fanart>https://i.imgur.com/hHSmFpn.png</fanart>
<link>http://ignoreme</link>
<externallink>https://raw.githubusercontent.com/Rhdelo/repositorioRHDELO/master/plugin.video.rhdeloiptv/videoclub.xml</externallink>
</item>

<item>
<title>NETFLIX</title>
<thumbnail>https://i.imgur.com/9AUuRgh.png</thumbnail>
<fanart>https://i.imgur.com/Ryl5aGB.png</fanart>
<link>http://ignoreme</link>
<externallink></externallink>
</item>

<item>
<title>Series Premium</title>
<thumbnail>https://i.imgur.com/OyMG57U.png</thumbnail>
<fanart>https://i.imgur.com/swpqQjF.png</fanart>
<link>http://ignoreme</link>
<externallink>https://raw.githubusercontent.com/Rhdelo/repositorioRHDELO/master/plugin.video.rhdeloiptv/videoclub.xml</externallink>
</item>

<item>
<title>Dibujos</title>
<thumbnail></thumbnail>
<fanart></fanart>
<link>http://ignoreme</link>
<externallink>https://raw.githubusercontent.com/Rhdelo/repositorioRHDELO/master/plugin.video.rhdeloiptv/seriesDibujos.xml</externallink>
</item>

<item>
<title>Documentales</title>
<thumbnail>https://i.imgur.com/Z6HPjvo.png</thumbnail>
<fanart>https://i.imgur.com/2y2Qm7M.png</fanart>
<link>http://ignoreme</link>
<externallink>https://raw.githubusercontent.com/Rhdelo/repositorioRHDELO/master/plugin.video.rhdeloiptv/menudocumentales.xml</externallink>
</item>

<item>
<title>Musica</title>
<thumbnail>https://i.imgur.com/EZXRP9M.png</thumbnail>
<fanart>https://i.imgur.com/zJcnl06.png</fanart>
<link>http://ignoreme</link>
<externallink>https://raw.githubusercontent.com/Rhdelo/repositorioRHDELO/master/plugin.video.rhdeloiptv/musicamenu.xml</externallink>
</item>

<item>
<title>Marvel</title>
<thumbnail>https://i.imgur.com/AQ9YIAB.png</thumbnail>
<fanart>https://i.imgur.com/g4r57T2.jpg</fanart>
<link>http://ignoreme</link>
<externallink></externallink>
</item>


